LICENSE
MANIFEST.in
README.md
requires.txt
setup.py
fighting/__init__.py
fighting/app.py
fighting/document.jinja2
fighting/res.py
fighting.egg-info/PKG-INFO
fighting.egg-info/SOURCES.txt
fighting.egg-info/dependency_links.txt
fighting.egg-info/not-zip-safe
fighting.egg-info/requires.txt
fighting.egg-info/top_level.txt