Metadata-Version: 1.1
Name: fighting
Version: 0.1.0
Summary: A simple JSON API web framework based on Flask
Home-page: https://github.com/ncuhome/fighting
Author: guyskk
Author-email: guyskk@qq.com
License: MIT
Platform: UNKNOWN
Classifier: Framework :: Flask
Classifier: Environment :: Web Environment
Classifier: Intended Audience :: Developers
Classifier: License :: OSI Approved :: MIT License
Classifier: Operating System :: OS Independent
Classifier: Programming Language :: Python :: 3 :: Only
Classifier: Topic :: Internet :: WWW/HTTP :: Dynamic Content
Classifier: Topic :: Software Development :: Libraries :: Python Modules
